TwitterAPI/BearerAuth.py
TwitterAPI/TwitterAPI.py
TwitterAPI/TwitterError.py
TwitterAPI/TwitterOAuth.py
TwitterAPI/TwitterPager.py
TwitterAPI/__init__.py
TwitterAPI/constants.py
TwitterAPI/credentials.txt
TwitterAPI_dylancaponi-2.7.5.dist-info/METADATA
TwitterAPI_dylancaponi-2.7.5.dist-info/WHEEL
TwitterAPI_dylancaponi-2.7.5.dist-info/top_level.txt
TwitterAPI_dylancaponi-2.7.5.dist-info/RECORD
